README.md
setup.py
src/vdk/plugin/ingest_file/ingest_file_plugin.py
src/vdk/plugin/ingest_file/ingestion_to_file.py
src/vdk_ingest_file.egg-info/PKG-INFO
src/vdk_ingest_file.egg-info/SOURCES.txt
src/vdk_ingest_file.egg-info/dependency_links.txt
src/vdk_ingest_file.egg-info/entry_points.txt
src/vdk_ingest_file.egg-info/requires.txt
src/vdk_ingest_file.egg-info/top_level.txt
tests/test_ingestion_to_file.py